excel_dbapi/__init__.py
excel_dbapi/connection.py
excel_dbapi/cursor.py
excel_dbapi/exceptions.py
excel_dbapi/engine/__init__.py
excel_dbapi/engine/base.py
excel_dbapi/engine/executor.py
excel_dbapi/engine/openpyxl_engine.py
excel_dbapi/engine/pandas_engine.py
excel_dbapi/engine/parser.py
excel_dbapi-2.0.0.dist-info/licenses/LICENSE
excel_dbapi-2.0.0.dist-info/METADATA
excel_dbapi-2.0.0.dist-info/WHEEL
excel_dbapi-2.0.0.dist-info/top_level.txt
excel_dbapi-2.0.0.dist-info/RECORD
