Metadata-Version: 2.4
Name: excel-dbapi
Version: 2.0.0
Summary: PEP 249 compliant DB-API driver for Excel files
Author-email: Yeongseon Choe <yeongseon.choe@gmail.com>
Requires-Python: >=3.9
License-File: LICENSE
Requires-Dist: pandas<3.0.0,>=2.0.0
Requires-Dist: openpyxl<4.0.0,>=3.1.0
Provides-Extra: dev
Requires-Dist: pytest<9.0.0,>=8.3.5; extra == "dev"
Requires-Dist: pytest-cov<5.0.0,>=4.1; extra == "dev"
Requires-Dist: black<26.0.0,>=25.1.0; extra == "dev"
Requires-Dist: isort<7.0.0,>=6.0.1; extra == "dev"
Requires-Dist: ruff<0.12.0,>=0.11.2; extra == "dev"
Requires-Dist: mypy<2.0.0,>=1.15.0; extra == "dev"
Requires-Dist: build; extra == "dev"
Requires-Dist: bandit<2.0.0,>=1.7.0; extra == "dev"
Requires-Dist: vulture<3.0,>=2.0; extra == "dev"
Requires-Dist: pre-commit; extra == "dev"
Requires-Dist: types-requests<3.0.0,>=2.28.0; extra == "dev"
Dynamic: license-file
